dotenv_loader/__init__.py
dotenv_loader-1.0.4.dist-info/licenses/LICENSE
dotenv_loader-1.0.4.dist-info/METADATA
dotenv_loader-1.0.4.dist-info/WHEEL
dotenv_loader-1.0.4.dist-info/top_level.txt
dotenv_loader-1.0.4.dist-info/RECORD
