Metadata-Version: 2.4
Name: dotenv-loader
Version: 1.0.4
Summary: Flexible and secure .env loader for Python projects with support for environment switching, nested project structures, and external configuration directories.
Author-email: Vladyslav Kozlovskyy <dbdevelop@gmail.com>
License: MIT
Project-URL: Homepage, https://dbdeveloper.github.io/dotenv-loader/
Project-URL: Repository, https://github.com/dbdeveloper/dotenv-loader
Project-URL: Bug Tracker, https://github.com/dbdeveloper/dotenv-loader/issues
Classifier: Development Status :: 5 - Production/Stable
Classifier: Intended Audience :: Developers
Classifier: License :: OSI Approved :: MIT License
Classifier: Programming Language :: Python
Classifier: Programming Language :: Python :: 3
Classifier: Programming Language :: Python :: 3.9
Classifier: Programming Language :: Python :: 3.10
Classifier: Programming Language :: Python :: 3.11
Classifier: Programming Language :: Python :: 3.12
Classifier: Programming Language :: Python :: 3.13
Classifier: Programming Language :: Python :: Implementation :: PyPy
Classifier: Operating System :: OS Independent
Classifier: Environment :: Console
Classifier: Topic :: Software Development :: Libraries :: Python Modules
Requires-Python: >=3.9
License-File: LICENSE
Requires-Dist: python-dotenv>=1.1.1
Provides-Extra: dev
Requires-Dist: black; extra == "dev"
Requires-Dist: flake8; extra == "dev"
Requires-Dist: mypy; extra == "dev"
Requires-Dist: build; extra == "dev"
Requires-Dist: twine; extra == "dev"
Requires-Dist: pytest; extra == "dev"
Requires-Dist: pytest-cov; extra == "dev"
Requires-Dist: coverage; extra == "dev"
Requires-Dist: codecov; extra == "dev"
Provides-Extra: test
Requires-Dist: pytest; extra == "test"
Requires-Dist: pytest-cov; extra == "test"
Requires-Dist: coverage; extra == "test"
Dynamic: license-file
